rraft_py-0.2.27.dist-info/METADATA
rraft_py-0.2.27.dist-info/WHEEL
rraft_py-0.2.27.dist-info/license_files/LICENSE
rraft/__init__.py
rraft/__init__.pyi
rraft/py.typed
rraft/rraft.cpython-311-darwin.so
rraft_py-0.2.27.dist-info/RECORD
