Metadata-Version: 2.1
Name: rraft-py
Version: 0.2.27
Classifier: Programming Language :: Rust
Classifier: Programming Language :: Python :: Implementation :: CPython
License-File: LICENSE
Summary: Unofficial Python Binding of the tikv/raft-rs
Keywords: raft,distributed-systems,consensus-algorithm,replication,distributed-database
Home-Page: https://github.com/lablup/rraft-py
Author: Lablup Inc.
License: Apache-2.0
Requires-Python: >=3.10
Project-URL: Source Code, https://github.com/lablup/rraft-py
